nntpserver/__init__.py
nntpserver/nntpserver.py
nntpserver-0.0.3.dist-info/LICENSE
nntpserver-0.0.3.dist-info/METADATA
nntpserver-0.0.3.dist-info/WHEEL
nntpserver-0.0.3.dist-info/top_level.txt
nntpserver-0.0.3.dist-info/RECORD
