Metadata-Version: 2.1
Name: nntpserver
Version: 0.0.3
Summary: No dependency, single file NNTP server library for developing modern, rfc3977-compliant (bridge) NNTP servers
Home-page: https://github.com/epilys/nntpserver.py
Author: Manos Pitsidianakis
Author-email: epilys@nessuent.xyz
License: UNKNOWN
Project-URL: Bug Tracker, https://github.com/epilys/nntpserver.py/issues
Platform: UNKNOWN
Classifier: Programming Language :: Python :: 3.7
Classifier: Topic :: Communications :: Usenet News
Classifier: License :: OSI Approved :: GNU Affero General Public License v3
Classifier: Operating System :: OS Independent
Requires-Python: >=3.7
License-File: LICENSE
